{
  "add_bf16": "elementwise",
  "barrier_vxm_deadlock": "deadlock",
  "cast": "cast",
  "cast_down_bf16": "cast",
  "cast_mxfp8_bf16": "cast",
  "cast_up_fp32": "cast",
  "cce": "cce",
  "cce_back2back": "cce",
  "cce_loopback_128B": "cce",
  "cce_loopback_256B": "cce",
  "cce_loopback_2act": "cce",
  "cce_loopback_2die": "cce",
  "cce_loopback_4act": "cce",
  "cce_loopback_512B": "cce",
  "cce_loopback_64B": "cce",
  "cce_loopback_8act": "cce",
  "cce_loopback_basic": "cce",
  "cce_loopback_cross": "cce",
  "cce_loopback_few": "cce",
  "cce_result_mcast": "cce",
  "cce_upper_subcluster": "cce",
  "clamp_fp32": "elementwise",
  "convert": "convert",
  "cvt": "convert",
  "cvt_bf16_fp8e4m3": "convert",
  "cvt_bf16_fp8e4m3_blk32": "convert",
  "cvt_bf16_fp8e4m3_rtz": "convert",
  "cvt_bf16_fp8e4m3_sat": "convert",
  "cvt_bf16_fp8e5m2": "convert",
  "cvt_fp32_fp8e4m3": "convert",
  "cvt_fp8e4m3_bf16": "convert",
  "cvt_fp8e4m3_fp32": "convert",
  "cvt_fp8e4m3_fp32_wide": "convert",
  "cvt_fp8e5m2_bf16": "convert",
  "deadlock": "deadlock",
  "eight_queens": "legacy",
  "elementwise": "elementwise",
  "exp_fp32": "elementwise",
  "legacy": "legacy",
  "linear_vme_bf16": "vme",
  "memcpy_fp32_local": "memory",
  "memory": "memory",
  "mul_bf16": "elementwise",
  "normalization": "normalization",
  "rmsnorm_bf16": "normalization",
  "rsqrt_fp32": "elementwise",
  "silu_bf16": "elementwise",
  "softmax_fp32": "normalization",
  "sub_bf16": "elementwise",
  "transpose_bf16": "elementwise",
  "vme": "vme",
  "vme_128tile": "vme",
  "vme_16act": "vme",
  "vme_16act_lmem": "vme",
  "vme_16tile": "vme",
  "vme_1tile": "vme",
  "vme_1tile_cd8192": "vme",
  "vme_1tile_xpose": "vme",
  "vme_24act": "vme",
  "vme_24act_lmem": "vme",
  "vme_2plane": "vme",
  "vme_2wave": "vme",
  "vme_32tile": "vme",
  "vme_32tile_2vxm": "vme",
  "vme_32tile_2vxm_chained": "vme",
  "vme_32tile_chained": "vme",
  "vme_32tile_polled": "vme",
  "vme_4act": "vme",
  "vme_4act_lmem": "vme",
  "vme_4tile": "vme",
  "vme_4tile_2vxm": "vme",
  "vme_4tile_cd2048": "vme",
  "vme_4tile_cd512": "vme",
  "vme_4tile_cd8192": "vme",
  "vme_4tile_fp8": "vme",
  "vme_4tile_large": "vme",
  "vme_4tile_xpose": "vme",
  "vme_4wave": "vme",
  "vme_64tile": "vme",
  "vme_7tile": "vme",
  "vme_7tile_polled": "vme",
  "vme_8act": "vme",
  "vme_8act_lmem": "vme",
  "vme_8tile": "vme",
  "vme_8tile_2acc": "vme",
  "vme_8tile_chained": "vme",
  "vme_8tile_polled": "vme",
  "vme_back2back": "vme",
  "vme_mixed_dtype_seq": "vme",
  "vme_odd_ncd": "vme",
  "vme_partial_vcores": "vme"
}
